{
  "version": 3,
  "middleware": {
    "/": {
      "files": [
        "server/edge-runtime-webpack.js",
        "server/src/middleware.js"
      ],
      "name": "src/middleware",
      "page": "/",
      "matchers": [
        {
          "regexp": "^(?:\\/(_next\\/data\\/[^/]{1,}))?(?:\\/((?!_next\\/static|_next\\/image|favicon.ico).*))(.json)?[\\/#\\?]?$",
          "originalSource": "/((?!_next/static|_next/image|favicon.ico).*)"
        }
      ],
      "wasm": [],
      "assets": [],
      "env": {
        "__NEXT_BUILD_ID": "a67n_5vATbxfUPj2UuhE6",
        "NEXT_SERVER_ACTIONS_ENCRYPTION_KEY": "fhQT22kjxf5iM66893dwyj+HfkqoUv1ogUXE2EUJuJM=",
        "__NEXT_PREVIEW_MODE_ID": "3580d6403e840136bb313e41e5cbca59",
        "__NEXT_PREVIEW_MODE_ENCRYPTION_KEY": "233d19478f617e653cce6681ff7839ae9049cfbc9cb820308013dd4e86b32205",
        "__NEXT_PREVIEW_MODE_SIGNING_KEY": "29c114c9c45e569bf4df4d6c4616ce3a6fe8a622eea2e902a6d3199170fe8528"
      }
    }
  },
  "functions": {},
  "sortedMiddleware": [
    "/"
  ]
}